cdifflint.py
cdifflint-1.0.1.data/scripts/cdifflint
cdifflint-1.0.1.dist-info/DESCRIPTION.rst
cdifflint-1.0.1.dist-info/METADATA
cdifflint-1.0.1.dist-info/RECORD
cdifflint-1.0.1.dist-info/WHEEL
cdifflint-1.0.1.dist-info/metadata.json
cdifflint-1.0.1.dist-info/top_level.txt
