Metadata-Version: 2.0
Name: cdifflint
Version: 1.0.1
Summary: View colored, incremental diff in a workspace, annotated with messages from your favorite linter.
Home-page: https://github.com/rgeoghegan/cdifflint
Author: Rory Geoghegan
Author-email: r.geoghegan@gmail.com
License: BSD-3
Keywords: colored incremental side-by-side diff,with lint messages
Platform: UNKNOWN
Classifier: Development Status :: 5 - Production/Stable
Classifier: Topic :: Utilities
Classifier: License :: OSI Approved :: BSD License
Classifier: Environment :: Console
Classifier: Intended Audience :: Developers
Classifier: Operating System :: MacOS :: MacOS X
Classifier: Operating System :: POSIX
Classifier: Operating System :: Unix
Classifier: Programming Language :: Python
Classifier: Programming Language :: Python :: 2
Classifier: Programming Language :: Python :: 3
Requires-Dist: cdiff (==0.9.8)
Requires-Dist: six (==1.10.0)
